LICENSE.txt
README.txt
dev.cfg
sample-prod.cfg
setup.py
start-cogplanet.py
cogplanet/__init__.py
cogplanet/controllers.py
cogplanet/easy_config.py
cogplanet/json.py
cogplanet/model.py
cogplanet/release.py
cogplanet/util.py
cogplanet.egg-info/PKG-INFO
cogplanet.egg-info/SOURCES.txt
cogplanet.egg-info/dependency_links.txt
cogplanet.egg-info/not-zip-safe
cogplanet.egg-info/paster_plugins.txt
cogplanet.egg-info/requires.txt
cogplanet.egg-info/sqlobject.txt
cogplanet.egg-info/top_level.txt
cogplanet/admin/__init__.py
cogplanet/admin/controller.py
cogplanet/config/__init__.py
cogplanet/config/app.cfg
cogplanet/config/log.cfg
cogplanet/static/css/style.css
cogplanet/static/images/favicon.ico
cogplanet/static/images/gloss-100.png
cogplanet/static/images/shadow-reverse-100.png
cogplanet/static/javascript/admin.js
cogplanet/templates/__init__.py
cogplanet/templates/feeds.html
cogplanet/templates/index.html
cogplanet/templates/layout.html
cogplanet/templates/login.html
cogplanet/templates/master.kid
cogplanet/templates/admin/__init__.py
cogplanet/templates/admin/entry.html
cogplanet/templates/admin/feed.html
cogplanet/templates/admin/import_feeds.html
cogplanet/templates/admin/index.html
cogplanet/templates/admin/layout.html
cogplanet/templates/admin/planet.html
cogplanet/tests/__init__.py
cogplanet/tests/test_controllers.py
cogplanet/tests/test_model.py
