Metadata-Version: 1.0
Name: cogplanet
Version: 0.8
Summary: A planet server written with TurboGears
Home-page: http://achievewith.us/projects/cogplanet
Author: Tim Freund
Author-email: tim@achievewith.us
License: MIT
Keywords: turbogears.app
Platform: UNKNOWN
Classifier: Development Status :: 3 - Alpha
Classifier: Operating System :: OS Independent
Classifier: Programming Language :: Python
Classifier: Topic :: Software Development :: Libraries :: Python Modules
Classifier: Framework :: TurboGears :: Applications
